Alexa-Payloads/Alexa.py
Alexa-Payloads/Card.py
Alexa-Payloads/Image.py
Alexa-Payloads/OutputSpeech.py
Alexa-Payloads/VoicePlatformABC.py
Alexa-Payloads/__init__.py
PyAlexaClient/Alexa.py
PyAlexaClient/Card.py
PyAlexaClient/Image.py
PyAlexaClient/OutputSpeech.py
PyAlexaClient/__init__.py
PyAlexaClient-0.3.dist-info/LICENSE
PyAlexaClient-0.3.dist-info/METADATA
PyAlexaClient-0.3.dist-info/WHEEL
PyAlexaClient-0.3.dist-info/top_level.txt
PyAlexaClient-0.3.dist-info/RECORD
